[
  {
    "name": "CSE_FEST_Preli",
    "description": "No description provided.",
    "html_url": "https://github.com/borno18/CSE_FEST_Preli",
    "stargazers_count": 0,
    "forks_count": 0,
    "language": "Python",
    "updated_at": "2026-06-26T17:38:42Z"
  },
  {
    "name": "SCSEF_Mock",
    "description": "No description provided.",
    "html_url": "https://github.com/borno18/SCSEF_Mock",
    "stargazers_count": 0,
    "forks_count": 0,
    "language": "Python",
    "updated_at": "2026-06-25T16:54:12Z"
  },
  {
    "name": "My-Portfolio",
    "description": "My portfolio",
    "html_url": "https://github.com/borno18/My-Portfolio",
    "stargazers_count": 0,
    "forks_count": 0,
    "language": "JavaScript",
    "updated_at": "2026-06-10T21:30:49Z"
  },
  {
    "name": "SWE-06132124-Project",
    "description": "Catch the Square is a simple, fast-paced arcade game built with Java Swing. Control the blue paddle at the bottom of the screen to catch falling red collectibles and rack up your score!",
    "html_url": "https://github.com/borno18/SWE-06132124-Project",
    "stargazers_count": 0,
    "forks_count": 0,
    "language": "Java",
    "updated_at": "2026-06-05T12:15:20Z"
  },
  {
    "name": "Gam4e",
    "description": "No description provided.",
    "html_url": "https://github.com/borno18/Gam4e",
    "stargazers_count": 0,
    "forks_count": 0,
    "language": "Markdown",
    "updated_at": "2026-06-05T09:28:52Z"
  },
  {
    "name": "Game_Project",
    "description": "No description provided.",
    "html_url": "https://github.com/borno18/Game_Project",
    "stargazers_count": 0,
    "forks_count": 0,
    "language": "Java",
    "updated_at": "2026-06-05T09:22:38Z"
  }
]